cite_exchange/__init__.py
cite_exchange/blocks.py
cite_exchange-0.2.0.dist-info/METADATA
cite_exchange-0.2.0.dist-info/WHEEL
cite_exchange-0.2.0.dist-info/licenses/LICENSE
cite_exchange-0.2.0.dist-info/RECORD
