Metadata-Version: 2.4
Name: cite_exchange
Version: 0.2.0
Summary: A Python library for reading data in CITE EXchange (CEX) format.
License-File: LICENSE
Requires-Python: >=3.14
Requires-Dist: ipython
Requires-Dist: pydantic>=2.12.5
Requires-Dist: requests
